{
  "region": "ca",
  "form_definitions": {
    "update_bank_info": {
      "field_definitions": {
        "routing_number": {
          "display_name": "Transit and Institution #",
          "hint_text": "",
          "input_type": "number",
          "pattern": "^[0-9]{8}$"
        },
        "account_number": {
          "display_name": "Account #",
          "hint_text": "",
          "input_type": "number",
          "pattern": "^[0-9]{1,30}$"
        },
        "tax_id_number": {
          "display_name": "Social Insurance #",
          "hint_text": "",
          "input_type": "number",
          "pattern": "^[0-9]{9}$"
        }
      }
    }
  }
}