{
  "region": "ca",
  "form_definitions": {
    "update_bank_info": {
      "field_definitions": {
        "routing_number": {
          "display_name": "Transit Number",
          "hint_text": "abcde123",
          "input_type": "alphanumeric",
          "pattern": "^[A-z]{5}[0-9]{3}$"
        },
        "account_number": {
          "display_name": "Account Number",
          "hint_text": "",
          "input_type": "number",
          "pattern": "^[0-9]{1,30}$"
        },
        "tax_id_number": {
          "display_name": "Social Insurance Number",
          "hint_text": "123456789",
          "input_type": "number",
          "pattern": "^[0-9]{9}$"
        }
      }
    }
  }
}